{
    "type": "FeatureCollection",
    "features": [
        {
            "type": "Feature",
            "geometry": {
                "type": "Point",
                "coordinates": [
                    9.671475699382732,
                    45.6993505368113,
                    0
                ]
            },
            "properties": {
                "name": "BERGAMO",
                "styleUrl": "#m_ylw-pushpin0",
                "styleHash": "43eda358",
                "styleMapHash": {
                    "normal": "#s_ylw-pushpin0",
                    "highlight": "#s_ylw-pushpin_hl0"
                }
            }
        },
        {
            "type": "Feature",
            "geometry": {
                "type": "Point",
                "coordinates": [
                    9.663412301034509,
                    45.70487496097293,
                    0
                ]
            },
            "properties": {
                "name": "CITTA' ALTA",
                "styleUrl": "#m_ylw-pushpin",
                "styleHash": "121c78b2",
                "styleMapHash": {
                    "normal": "#s_ylw-pushpin",
                    "highlight": "#s_ylw-pushpin_hl"
                }
            }
        }
    ]
}